qstest/__init__.py
qstest/cmalgorithm_wrapper.py
qstest/qstest.py
qstest/quality_functions.py
qstest/size_functions.py
qstest-1.0.5.dist-info/DESCRIPTION.rst
qstest-1.0.5.dist-info/METADATA
qstest-1.0.5.dist-info/RECORD
qstest-1.0.5.dist-info/WHEEL
qstest-1.0.5.dist-info/metadata.json
qstest-1.0.5.dist-info/top_level.txt
