Metadata-Version: 2.0
Name: qstest
Version: 1.0.5
Summary: Python code for the (q,s)-test
Home-page: https://github.com/skojaku/qstest.git
Author: Sadamori Kojaku
Author-email: sadamori.koujaku@bristol.ac.uk
License: MIT
Keywords: network community significance test
Platform: UNKNOWN
Classifier: Development Status :: 3 - Alpha
Classifier: Intended Audience :: Science/Research
Classifier: Topic :: Software Development
Classifier: License :: OSI Approved :: MIT License
Classifier: Programming Language :: Python :: 2.7
Classifier: Programming Language :: Python :: 3.4
Classifier: Programming Language :: Python :: 3.5
Classifier: Programming Language :: Python :: 3.6
Requires-Dist: decorator
Requires-Dist: networkx (>=2.0)
Requires-Dist: numpy
Requires-Dist: python-louvain (==0.9)
Requires-Dist: scipy (>=1.0)
